django_validated_jsonfield/__init__.py
django_validated_jsonfield/converter.py
django_validated_jsonfield/fields.py
django_validated_jsonfield/inspectors.py
django_validated_jsonfield/serializers.py
django_validated_jsonfield/yasg.py
django_validated_jsonfield-1.2.3.dist-info/LICENSE.md
django_validated_jsonfield-1.2.3.dist-info/WHEEL
django_validated_jsonfield-1.2.3.dist-info/METADATA
django_validated_jsonfield-1.2.3.dist-info/RECORD
