Metadata-Version: 2.1
Name: django-validated-jsonfield
Version: 1.2.3
Summary: Add a schema with validation to your jsonfield
Home-page: https://gitlab.com/loic.quertenmont/django_validated_jsonfield
License: MIT
Keywords: django,JSONField,json-schema,drf-yasg,coreapi
Author: Loic Quertenmont
Author-email: loic@youmeal.io
Requires-Python: >=3.7,<4.0
Classifier: License :: OSI Approved :: MIT License
Classifier: Programming Language :: Python :: 3
Classifier: Programming Language :: Python :: 3.7
Classifier: Programming Language :: Python :: 3.8
Classifier: Programming Language :: Python :: 3.9
Requires-Dist: django (>=2.2.0)
Requires-Dist: djangorestframework (>=3.11.0)
Requires-Dist: drf_yasg
Requires-Dist: jsonschema
Requires-Dist: jsonschema-to-openapi (>=0.2.1)
Project-URL: Repository, https://gitlab.com/loic.quertenmont/django_validated_jsonfield
